neuralnest/__init__.py
neuralnest/config.py
neuralnest/hello_milvus.py
neuralnest/load_models.py
neuralnest/vector_search.py
neuralnest/vectorizers.py
neuralnest-0.1.0.dist-info/METADATA
neuralnest-0.1.0.dist-info/WHEEL
neuralnest-0.1.0.dist-info/RECORD
