Metadata-Version: 2.1
Name: neuralnest
Version: 0.1.0
Summary: NeuralNest: An open-source personal AI assistant designed for seamless data integration from various sources, offering versatile connections to Language Learning Models (LLMs), enhanced security, and human-in-the-loop options for a personalized AI experience.
Author: Foxicution
Author-email: foxicution@gmail.com
Requires-Python: >=3.10,<4.0
Classifier: Programming Language :: Python :: 3
Classifier: Programming Language :: Python :: 3.10
Classifier: Programming Language :: Python :: 3.11
Requires-Dist: accelerate (>=0.22.0,<0.23.0)
Requires-Dist: bitsandbytes (>=0.41.1,<0.42.0)
Requires-Dist: llama-index (>=0.8.11,<0.9.0)
Requires-Dist: protobuf (>=4.24.2,<5.0.0)
Requires-Dist: pymilvus (>=2.3.0,<3.0.0)
Requires-Dist: sentence-transformers (>=2.2.2,<3.0.0)
Requires-Dist: sentencepiece (>=0.1.99,<0.2.0)
